ocomone/__init__.py
ocomone/logging.py
ocomone/resources.py
ocomone/session.py
ocomone/timer.py
ocomone-0.4.3.dist-info/LICENSE
ocomone-0.4.3.dist-info/WHEEL
ocomone-0.4.3.dist-info/METADATA
ocomone-0.4.3.dist-info/RECORD
